flask_jwt_router/__init__.py
flask_jwt_router/_authentication.py
flask_jwt_router/_config.py
flask_jwt_router/_entity.py
flask_jwt_router/_jwt_routes.py
flask_jwt_router/_routing.py
flask_jwt_router/oauth2/__init__.py
flask_jwt_router/oauth2/_base.py
flask_jwt_router/oauth2/_exceptions.py
flask_jwt_router/oauth2/_urls.py
flask_jwt_router/oauth2/google.py
flask_jwt_router/oauth2/http_requests.py
flask_jwt_router-0.1.9.dist-info/LICENSE.txt
flask_jwt_router-0.1.9.dist-info/METADATA
flask_jwt_router-0.1.9.dist-info/WHEEL
flask_jwt_router-0.1.9.dist-info/top_level.txt
flask_jwt_router-0.1.9.dist-info/RECORD
