Metadata-Version: 2.1
Name: flask-jwt-router
Version: 0.1.9
Summary: Flask JWT Router is a Python library that adds authorised routes to a Flask app
Home-page: https://github.com/joegasewicz/Flask-JWT-Router
Author: Joe Gasewicz
Author-email: joegasewicz@gmail.com
License: UNKNOWN
Platform: UNKNOWN
Classifier: Development Status :: 3 - Alpha
Classifier: Programming Language :: Python :: 3.6
Classifier: Programming Language :: Python :: 3.7
Classifier: Programming Language :: Python :: 3.8
Classifier: Programming Language :: Python :: 3.9
Classifier: License :: OSI Approved :: GNU General Public License v3 or later (GPLv3+)
Classifier: Operating System :: OS Independent
